string_to_int_to_string/__init__.py
string_to_int_to_string/example_conversion.py
string_to_int_to_string/main.py
string_to_int_to_string/stits_main.py
string_to_int_to_string/stits_utils.py
string_to_int_to_string/string_to_int_to_string.py
string_to_int_to_string-0.1.dist-info/LICENSE
string_to_int_to_string-0.1.dist-info/METADATA
string_to_int_to_string-0.1.dist-info/WHEEL
string_to_int_to_string-0.1.dist-info/top_level.txt
string_to_int_to_string-0.1.dist-info/RECORD
