Metadata-Version: 2.1
Name: string-to-int-to-string
Version: 0.1
Summary: One-to-one & deterministic functions for converting any string to an int, and any int to a string
Home-page: https://github.com/rptine/string-to-int-to-string.git
Author: Ryan Tine
Author-email: ryanptine@gmail.com
License: MIT
Platform: UNKNOWN
